appcraft/__init__.py
appcraft/scripts/__init__.py
appcraft/scripts/add_template.py
appcraft/scripts/cli.py
appcraft/scripts/create_init.py
appcraft/scripts/create_runner.py
appcraft/scripts/list_templates.py
appcraft/scripts/project_init.py
appcraft/templates/template_abc.py
appcraft/templates/template_manager.py
appcraft/templates/base/__init__.py
appcraft/templates/base/files/Pipfile
appcraft/templates/base/files/README.md
appcraft/templates/base/files/run
appcraft/templates/base/files/run_tools
appcraft/templates/base/files/application/dtos/app_dto.py
appcraft/templates/base/files/application/dtos/user_dto.py
appcraft/templates/base/files/application/dtos/interfaces/__init__.py
appcraft/templates/base/files/application/mappers/app_mapper.py
appcraft/templates/base/files/application/mappers/user_mapper.py
appcraft/templates/base/files/application/mappers/interfaces/__init__.py
appcraft/templates/base/files/application/services/app_service.py
appcraft/templates/base/files/application/services/user_service.py
appcraft/templates/base/files/application/services/interfaces/__init__.py
appcraft/templates/base/files/config/app.toml
appcraft/templates/base/files/config/theme.json
appcraft/templates/base/files/docs/Makefile
appcraft/templates/base/files/docs/make.bat
appcraft/templates/base/files/docs/source/conf.py
appcraft/templates/base/files/docs/source/index.rst
appcraft/templates/base/files/docs/source/modules.rst
appcraft/templates/base/files/domain/filters/__init__.py
appcraft/templates/base/files/domain/interfaces/repositories/__init__.py
appcraft/templates/base/files/domain/interfaces/repositories/user_repository.py
appcraft/templates/base/files/domain/models/app.py
appcraft/templates/base/files/domain/models/user.py
appcraft/templates/base/files/domain/models/exceptions/__init__.py
appcraft/templates/base/files/domain/models/exceptions/user_model_not_found.py
appcraft/templates/base/files/domain/models/inspector/__init__.py
appcraft-0.5.3.dist-info/METADATA
appcraft-0.5.3.dist-info/WHEEL
appcraft-0.5.3.dist-info/entry_points.txt
appcraft-0.5.3.dist-info/top_level.txt
appcraft-0.5.3.dist-info/RECORD
