Metadata-Version: 2.2
Name: appcraft
Version: 0.5.3
Summary: Appcraft is a modular framework designed to simplify software development by providing a structured and extensible architecture. It enables developers to create and manage complex applications with ease, ensuring scalability and maintainability.
Home-page: https://github.com/duxtec/appcraft
Author-email: Dux Tecnologia <contato@tpereira.com.br>
Classifier: Programming Language :: Python :: 3
Classifier: License :: OSI Approved :: MIT License
Classifier: Operating System :: OS Independent
Requires-Python: >=3.6
Requires-Dist: prompt_toolkit
Requires-Dist: toml
Dynamic: home-page
